xmptools/__init__.py
xmptools/xmptools.py
xmptools-0.6.7.dist-info/licenses/LICENSE
xmptools-0.6.7.dist-info/METADATA
xmptools-0.6.7.dist-info/WHEEL
xmptools-0.6.7.dist-info/top_level.txt
xmptools-0.6.7.dist-info/RECORD
