Metadata-Version: 2.4
Name: xmptools
Version: 0.6.7
Summary: XMP support for RDFLib, tools for manipulating XMP metadata
Author-email: Ora Lassila <ora@somanyaircraft.com>
License-Expression: BSD-3-Clause
Project-URL: Homepage, https://gitlab.com/somanyaircraft/xmptools
Classifier: Development Status :: 4 - Beta
Classifier: Programming Language :: Python :: 3
Classifier: Operating System :: OS Independent
Requires-Python: >=3.8
License-File: LICENSE
Dynamic: license-file
